[
{
"quote": "The person you are becoming // will cost you the person you used to be",
"background_keyword": "ocean waves",
"caption": "Growth is expensive. Are you willing to pay the price of evolving? #cinematic #lifequotes #mindset #growth #healing"
},
{
"quote": "You are not falling behind // you are just growing at a different pace",
"background_keyword": "river flowing",
"caption": "Stop comparing your Chapter 2 to someone else’s Chapter 10. #cinematic #lifequotes #mindset #growth #healing"
},
{
"quote": "Some paths only clear up // once you decide to start walking through them",
"background_keyword": "foggy pine trees",
"caption": "Clarity follows action, not the other way around. Trust the process. #cinematic #lifequotes #mindset #growth #healing"
},
{
"quote": "The peace you find alone // is worth every person you had to leave",
"background_keyword": "birds flying sky",
"caption": "Protecting your energy isn't selfish; it's necessary for survival. #cinematic #lifequotes #mindset #growth #healing"
},
{
"quote": "Healing looks like silence // when you used to feel the need to explain",
"background_keyword": "cloudy sky",
"caption": "Have you noticed how much quieter your mind is lately? #cinematic #lifequotes #mindset #growth #healing"
},
{
"quote": "We lose the best things // by trying to hold onto them too tight",
"background_keyword": "falling snow",
"caption": "True freedom is letting things come and go as they please. #cinematic #lifequotes #mindset #growth #healing"
},
{
"quote": "Every calm you see in me // has graves of the chaos I survived",
"background_keyword": "still lake water",
"caption": "The quietest souls often have the loudest pasts. Respect the journey. #cinematic #lifequotes #mindset #growth #healing"
},
{
"quote": "Your life is not a race // it is a garden that needs time",
"background_keyword": "blooming flowers",
"caption": "Stop rushing the seasons of your life. Everything blooms when ready. #cinematic #lifequotes #mindset #growth #healing"
},
{
"quote": "The hardest part of moving on // is not looking back at the fire",
"background_keyword": "sunset horizon",
"caption": "Stop checking on things that no longer belong to you. #cinematic #lifequotes #mindset #growth #healing"
},
{
"quote": "You were never too much // you were simply in the wrong forest",
"background_keyword": "deep green forest",
"caption": "The right environment will always celebrate what the wrong one tolerates. #cinematic #lifequotes #mindset #growth #healing"
},
{
"quote": "Forgiveness is the gift // you give yourself to finally walk away light",
"background_keyword": "mountain peaks",
"caption": "Losing the resentment is the only way to climb higher. #cinematic #lifequotes #mindset #growth #healing"
},
{
"quote": "The trees do not panic // when the leaves begin to fall away",
"background_keyword": "autumn leaves falling",
"caption": "Letting go is a natural part of being alive. Let it happen. #cinematic #lifequotes #mindset #growth #healing"
},
{
"quote": "A quiet mind is a power // that the world cannot take from you",
"background_keyword": "starry night sky",
"caption": "In a world of noise, your inner peace is your greatest weapon. #cinematic #lifequotes #mindset #growth #healing"
},
{
"quote": "The sun does not ask // if its light is enough for everyone",
"background_keyword": "rising sun",
"caption": "Stop seeking validation for just existing. You are already enough. #cinematic #lifequotes #mindset #growth #healing"
},
{
"quote": "We are all just stars // trying to find our way back home",
"background_keyword": "milky way galaxy",
"caption": "Does it ever feel like you're searching for something you can't name? #cinematic #lifequotes #mindset #growth #healing"
},
{
"quote": "Your worth is not measured // by how much you do in a day",
"background_keyword": "rain falling",
"caption": "Rest is productive. You are a human being, not a machine. #cinematic #lifequotes #mindset #growth #healing"
},
{
"quote": "The tide goes out today // so it can return stronger tomorrow morning",
"background_keyword": "beach shoreline",
"caption": "Low points are just preparation for the next big wave. #cinematic #lifequotes #mindset #growth #healing"
},
{
"quote": "Stop trying to fix things // that were meant to stay broken forever",
"background_keyword": "thunderstorm clouds",
"caption": "Some endings are actually rescues in disguise. Let them be. #cinematic #lifequotes #mindset #growth #healing"
},
{
"quote": "The most beautiful peaks // require the most difficult walks to reach them",
"background_keyword": "snowy mountains",
"caption": "The view is better when you know what it took to get there. #cinematic #lifequotes #mindset #growth #healing"
},
{
"quote": "You are the wide sky // everything else is just the passing weather",
"background_keyword": "blue sky clouds",
"caption": "Don't let a temporary storm define your permanent identity. #cinematic #lifequotes #mindset #growth #healing"
},
{
"quote": "Sometimes you have to vanish // to see who is still looking",
"background_keyword": "thick fog",
"caption": "Absence clarifies who truly values your presence in their life. #cinematic #lifequotes #mindset #growth #healing"
},
{
"quote": "True strength is being soft // in a world that is very hard",
"background_keyword": "mossy rocks",
"caption": "Don't let the world turn your heart into stone. Stay kind. #cinematic #lifequotes #mindset #growth #healing"
},
{
"quote": "The moon is still whole // even when it is not fully visible",
"background_keyword": "crescent moon",
"caption": "You don't have to be 'on' all the time to be complete. #cinematic #lifequotes #mindset #growth #healing"
},
{
"quote": "Water carves the stone // not by force but by staying consistent",
"background_keyword": "waterfall rocks",
"caption": "Small, daily habits will always beat occasional grand gestures. #cinematic #lifequotes #mindset #growth #healing"
},
{
"quote": "Growth is often very quiet // while destruction makes a lot of noise",
"background_keyword": "grass blowing wind",
"caption": "Just because you can't hear it doesn't mean it isn't happening. #cinematic #lifequotes #mindset #growth #healing"
},
{
"quote": "You cannot find your future // by living in your past mistakes",
"background_keyword": "desert dunes",
"caption": "The rear-view mirror is small for a reason. Look ahead. #cinematic #lifequotes #mindset #growth #healing"
},
{
"quote": "The best version of you // is waiting for your permission to exist",
"background_keyword": "morning mist",
"caption": "What are you waiting for? The world needs your light today. #cinematic #lifequotes #mindset #growth #healing"
},
{
"quote": "Not every door that opens // is a door you should walk through",
"background_keyword": "canyon walls",
"caption": "Discernment is the highest form of self-care. Choose wisely. #cinematic #lifequotes #mindset #growth #healing"
},
{
"quote": "Happiness is a slow walk // through the woods of your own soul",
"background_keyword": "sunlight through trees",
"caption": "It was never at the finish line. It was always in the steps. #cinematic #lifequotes #mindset #growth #healing"
},
{
"quote": "To be at peace now // you must let the old versions die",
"background_keyword": "burning embers",
"caption": "Rebirth requires the courage to say goodbye to who you were. #cinematic #lifequotes #mindset #growth #healing"
}
]